iran_stock/__init__.py
iran_stock/const.py
iran_stock/datatable.py
iran_stock/exceptions.py
iran_stock/fundamental.py
iran_stock/historical.py
iran_stock/main.py
iran_stock/tools.py
iran_stock/database/__init__.py
iran_stock-0.1.2.dist-info/LICENSE.txt
iran_stock-0.1.2.dist-info/METADATA
iran_stock-0.1.2.dist-info/WHEEL
iran_stock-0.1.2.dist-info/top_level.txt
iran_stock-0.1.2.dist-info/RECORD
