Metadata-Version: 2.1
Name: iran-stock
Version: 0.1.2
Summary: Get access to Iran's stock information
Home-page: https://github.com/J-Yaghoubi/iran_stock
Author: Seyed Jafar Yaghoubi
Author-email: algo3xp3rt@gmail.com
License: MIT
Platform: UNKNOWN
Classifier: License :: OSI Approved :: MIT License
Classifier: Programming Language :: Python :: 3.7
Classifier: Operating System :: OS Independent
Requires-Python: >=3.7, <4
License-File: LICENSE.txt
Requires-Dist: requests
Requires-Dist: beautifulsoup4
Requires-Dist: pandas
